ebokeh/__init__.py
ebokeh/plotting/__init__.py
ebokeh/plotting/figure.py
ebokeh-0.1.3.dist-info/DESCRIPTION.rst
ebokeh-0.1.3.dist-info/METADATA
ebokeh-0.1.3.dist-info/RECORD
ebokeh-0.1.3.dist-info/WHEEL
ebokeh-0.1.3.dist-info/metadata.json
ebokeh-0.1.3.dist-info/top_level.txt
