Metadata-Version: 2.0
Name: ebokeh
Version: 0.1.3
Summary: Enhanced Ebokeh, make charting much easier!
Home-page: https://github.com/xbanke/ebokeh
Author: quantpy
Author-email: quantpy@gmail.com
License: MIT
Keywords: bokeh,charts
Platform: UNKNOWN
Classifier: Development Status :: 4 - Beta
Classifier: Environment :: Console
Classifier: Intended Audience :: Developers
Classifier: License :: OSI Approved :: MIT License
Classifier: Operating System :: OS Independent
Classifier: Programming Language :: Python
Classifier: Programming Language :: Python :: Implementation
Classifier: Programming Language :: Python :: 2
Classifier: Programming Language :: Python :: 2.7
Classifier: Programming Language :: Python :: 3
Classifier: Programming Language :: Python :: 3.4
Classifier: Programming Language :: Python :: 3.5
Classifier: Programming Language :: Python :: 3.6
Classifier: Topic :: Software Development :: Libraries
Requires-Dist: bokeh
Requires-Dist: pandas
